sqlite_framework/__init__.py
sqlite_framework/project_info.py
sqlite_framework/component/__init__.py
sqlite_framework/component/component.py
sqlite_framework/component/factory.py
sqlite_framework/component/components/__init__.py
sqlite_framework/component/components/version_info.py
sqlite_framework/component/migrate/__init__.py
sqlite_framework/component/migrate/exception.py
sqlite_framework/component/migrate/migrator.py
sqlite_framework/component/migrate/strategy.py
sqlite_framework/component/migrate/strategies/__init__.py
sqlite_framework/component/migrate/strategies/create.py
sqlite_framework/component/migrate/strategies/none.py
sqlite_framework/component/migrate/strategies/upgrade_or_downgrade.py
sqlite_framework/log/__init__.py
sqlite_framework/log/impl.py
sqlite_framework/log/logger.py
sqlite_framework/session/__init__.py
sqlite_framework/session/session.py
sqlite_framework/sql/__init__.py
sqlite_framework/sql/item/__init__.py
sqlite_framework/sql/item/base.py
sqlite_framework/sql/item/column.py
sqlite_framework/sql/item/table.py
sqlite_framework/sql/item/constants/__init__.py
sqlite_framework/sql/item/constants/conflict_resolution.py
sqlite_framework/sql/item/constants/operator.py
sqlite_framework/sql/item/constants/order_mode.py
sqlite_framework/sql/item/constants/type.py
sqlite_framework/sql/item/constraint/__init__.py
sqlite_framework/sql/item/constraint/base.py
sqlite_framework/sql/item/constraint/column/__init__.py
sqlite_framework/sql/item/constraint/column/base.py
sqlite_framework/sql/item/constraint/column/column.py
sqlite_framework/sql/item/constraint/column/default.py
sqlite_framework/sql/item/constraint/column/simple.py
sqlite_framework/sql/item/constraint/foreign_key/__init__.py
sqlite_framework/sql/item/constraint/foreign_key/change.py
sqlite_framework/sql/item/constraint/foreign_key/references.py
sqlite_framework/sql/item/constraint/table/__init__.py
sqlite_framework/sql/item/constraint/table/base.py
sqlite_framework-1.2.0.dist-info/METADATA
sqlite_framework-1.2.0.dist-info/RECORD
sqlite_framework-1.2.0.dist-info/WHEEL
sqlite_framework-1.2.0.dist-info/top_level.txt
